[
  {
    "title": "ISO 9001 인증서 (품질경영)",
    "category": "인증서",
    "description": "GERMAN CERT 인증번호: GQ-211254. 품질경영 시스템 국제 표준 인증.",
    "url": "/files/library/iso-9001-cert.pdf",
    "type": "PDF",
    "size": "70KB",
    "date": "2026-05-19",
    "published": true
  },
  {
    "title": "ISO 14001 인증서 (환경경영)",
    "category": "인증서",
    "description": "GERMAN CERT 인증번호: GE-210491. 환경경영 시스템 국제 표준 인증.",
    "url": "/files/library/iso-14001-cert.pdf",
    "type": "PDF",
    "size": "71KB",
    "date": "2026-05-19",
    "published": true
  },
  {
    "title": "ISO 45001 인증서 (안전보건경영)",
    "category": "인증서",
    "description": "GERMAN CERT 인증번호: GO-251038. 안전보건경영 시스템 국제 표준 인증.",
    "url": "/files/library/iso-45001-cert.pdf",
    "type": "PDF",
    "size": "197KB",
    "date": "2026-05-19",
    "published": true
  },
  {
    "title": "사업자등록증",
    "category": "인증서",
    "description": "㈜삼선엔지니어링 사업자등록증 (업무용).",
    "url": "/files/library/business-registration.pdf",
    "type": "PDF",
    "size": "797KB",
    "date": "2026-05-19",
    "published": true
  },
  {
    "title": "전기공사업 등록증",
    "category": "인증서",
    "description": "전라남도 전기공사업 등록증 (등록번호: 전남-02289호).",
    "url": "/files/library/electrical-construction-cert.pdf",
    "type": "PDF",
    "size": "174KB",
    "date": "2026-05-19",
    "published": true
  },
  {
    "title": "뿌리기업확인서",
    "category": "인증서",
    "description": "산업통상자원부 발급 뿌리기업확인서 (유효기간 2025.08.05 ~ 2028.08.04).",
    "url": "/files/library/root-company-cert.pdf",
    "type": "PDF",
    "size": "—",
    "date": "2026-05-19",
    "published": true
  },
  {
    "title": "항만운송관련사업(선박수리업) 등록증",
    "category": "인증서",
    "description": "국토교통부 발급 항만운송관련사업 등록증 (선박수리업).",
    "url": "/files/library/marine-repair-registration.pdf",
    "type": "PDF",
    "size": "—",
    "date": "2026-05-19",
    "published": true
  },
  {
    "title": "공장등록증",
    "category": "인증서",
    "description": "전라남도 발급 공장등록증명 (자체 가공·제작 시설 보유 증빙).",
    "url": "/files/library/factory-registration.pdf",
    "type": "PDF",
    "size": "—",
    "date": "2026-05-19",
    "published": true
  },
  {
    "title": "특허 등록증 (제10-1689014호)",
    "category": "인증서",
    "description": "등록 특허 제10-1689014호.",
    "url": "/files/library/patent-1689014.pdf",
    "type": "PDF",
    "size": "—",
    "date": "2026-05-19",
    "published": true
  },
  {
    "title": "특허 등록증 (제10-1902987호)",
    "category": "인증서",
    "description": "등록 특허 제10-1902987호.",
    "url": "/files/library/patent-1902987.pdf",
    "type": "PDF",
    "size": "—",
    "date": "2026-05-19",
    "published": true
  }
]